bumpkin/__init__.py
bumpkin/__main__.py
bumpkin/bumpkin.py
standard_bumpkin-2021.9.12.dist-info/LICENSE
standard_bumpkin-2021.9.12.dist-info/METADATA
standard_bumpkin-2021.9.12.dist-info/WHEEL
standard_bumpkin-2021.9.12.dist-info/entry_points.txt
standard_bumpkin-2021.9.12.dist-info/top_level.txt
standard_bumpkin-2021.9.12.dist-info/RECORD
